uvtrick/__init__.py
uvtrick-0.4.2.dist-info/METADATA
uvtrick-0.4.2.dist-info/WHEEL
uvtrick-0.4.2.dist-info/licenses/LICENSE
uvtrick-0.4.2.dist-info/RECORD
