Metadata-Version: 2.4
Name: uvtrick
Version: 0.4.2
Summary: A fun party trick to run Python code from another venv into this one.
Project-URL: Homepage, https://github.com/koaning/uvtrick
Project-URL: Repository, https://github.com/koaning/uvtrick.git
Author: Vincent D Warmerdam
License: MIT
License-File: LICENSE
Classifier: Intended Audience :: Developers
Classifier: License :: OSI Approved :: MIT License
Requires-Python: >=3.8
Requires-Dist: cloudpickle>=2.0.0
Requires-Dist: uv
